torch_installer/__init__.py
torch_installer/cli.py
torch_installer/installer.py
torch_installer_coff33ninja-1.0.3.dist-info/licenses/LICENSE
torch_installer_coff33ninja-1.0.3.dist-info/METADATA
torch_installer_coff33ninja-1.0.3.dist-info/WHEEL
torch_installer_coff33ninja-1.0.3.dist-info/entry_points.txt
torch_installer_coff33ninja-1.0.3.dist-info/top_level.txt
torch_installer_coff33ninja-1.0.3.dist-info/RECORD
