Metadata-Version: 2.4
Name: torch-installer-coff33ninja
Version: 1.0.3
Summary: An intelligent, autonomous PyTorch installer that automatically detects your system, GPU, and CUDA configuration
Home-page: https://github.com/coff33ninja/torch-installer
Author: coff33ninja
Author-email: coff33ninja <coff33ninja69@gmail.com>
Maintainer-email: coff33ninja <coff33ninja69@gmail.com>
License: MIT
Project-URL: Homepage, https://github.com/coff33ninja/torch-installer
Project-URL: Repository, https://github.com/coff33ninja/torch-installer
Project-URL: Issues, https://github.com/coff33ninja/torch-installer/issues
Project-URL: Documentation, https://github.com/coff33ninja/torch-installer#readme
Keywords: pytorch,torch,cuda,gpu,installer,machine-learning,deep-learning
Classifier: Development Status :: 4 - Beta
Classifier: Intended Audience :: Developers
Classifier: Intended Audience :: Science/Research
Classifier: Operating System :: OS Independent
Classifier: Programming Language :: Python :: 3
Classifier: Programming Language :: Python :: 3.7
Classifier: Programming Language :: Python :: 3.8
Classifier: Programming Language :: Python :: 3.9
Classifier: Programming Language :: Python :: 3.10
Classifier: Programming Language :: Python :: 3.11
Classifier: Programming Language :: Python :: 3.12
Classifier: Topic :: Scientific/Engineering :: Artificial Intelligence
Classifier: Topic :: Software Development :: Libraries :: Python Modules
Classifier: Topic :: System :: Installation/Setup
Requires-Python: >=3.7
License-File: LICENSE
Provides-Extra: dev
Requires-Dist: pytest>=6.0; extra == "dev"
Requires-Dist: black>=21.0; extra == "dev"
Requires-Dist: flake8>=3.8; extra == "dev"
Requires-Dist: twine>=3.0; extra == "dev"
Requires-Dist: build>=0.7; extra == "dev"
Dynamic: author
Dynamic: home-page
Dynamic: license-file
Dynamic: requires-python
